xarray_validate/__init__.py
xarray_validate/_match.py
xarray_validate/_version.py
xarray_validate/base.py
xarray_validate/components.py
xarray_validate/converters.py
xarray_validate/dataarray.py
xarray_validate/dataset.py
xarray_validate/testing.py
xarray_validate/types.py
xarray_validate/units.py
xarray_validate-0.0.5.dist-info/METADATA
xarray_validate-0.0.5.dist-info/WHEEL
xarray_validate-0.0.5.dist-info/licenses/LICENSE
xarray_validate-0.0.5.dist-info/RECORD
