Metadata-Version: 2.4
Name: xarray-validate
Version: 0.0.5
Summary: A lightweight xarray validation library
Project-URL: Homepage, https://github.com/leroyvn/xarray-validate/
Project-URL: Documentation, https://xarray-validate.readthedocs.io/
Project-URL: Changelog, https://github.com/leroyvn/xarray-validate/blob/main/CHANGELOG.md
Project-URL: Issues, https://github.com/leroyvn/xarray-validate/issues/
Project-URL: Repository, https://github.com/leroyvn/xarray-validate/
Author-email: Vincent Leroy <vincent.leroy@rayference.eu>
License-File: LICENSE
Classifier: Development Status :: 4 - Beta
Classifier: License :: OSI Approved :: MIT License
Classifier: Programming Language :: Python :: 3.8
Classifier: Programming Language :: Python :: 3.9
Classifier: Programming Language :: Python :: 3.10
Classifier: Programming Language :: Python :: 3.11
Classifier: Programming Language :: Python :: 3.12
Classifier: Programming Language :: Python :: 3.13
Classifier: Programming Language :: Python :: 3.14
Classifier: Topic :: Scientific/Engineering
Requires-Python: >=3.8
Requires-Dist: attrs
Requires-Dist: numpy
Requires-Dist: xarray
Provides-Extra: dask
Requires-Dist: dask; extra == 'dask'
Provides-Extra: units
Requires-Dist: pint; extra == 'units'
Provides-Extra: yaml
Requires-Dist: ruamel-yaml; extra == 'yaml'
